lavender_ccgan/CcGAN_SAGAN.py
lavender_ccgan/__init__.py
lavender_ccgan/cGAN_SAGAN.py
lavender_ccgan/cGAN_concat_SAGAN.py
lavender_ccgan-0.0.4.dist-info/licenses/LICENSE
lavender_ccgan-0.0.4.dist-info/METADATA
lavender_ccgan-0.0.4.dist-info/WHEEL
lavender_ccgan-0.0.4.dist-info/top_level.txt
lavender_ccgan-0.0.4.dist-info/RECORD
