Metadata-Version: 2.4
Name: Lavender-CcGAN
Version: 0.0.4
Summary: A pip package of model CcGAN.
Home-page: https://github.com/Zeyu-Xie/Lavender-CcGAN
Author: Zeyu Xie
Author-email: xie.zeyu20@gmail.com
Classifier: Programming Language :: Python :: 3
Classifier: License :: OSI Approved :: GNU General Public License v3 (GPLv3)
Classifier: Operating System :: OS Independent
Requires-Python: >=3.6
License-File: LICENSE
Dynamic: author
Dynamic: author-email
Dynamic: classifier
Dynamic: description
Dynamic: description-content-type
Dynamic: home-page
Dynamic: license-file
Dynamic: requires-python
Dynamic: summary
